[{"url":"https://api.github.com/repos/iperov/DeepFaceLab/issues/comments/527802237","html_url":"https://github.com/iperov/DeepFaceLab/issues/390#issuecomment-527802237","issue_url":"https://api.github.com/repos/iperov/DeepFaceLab/issues/390","id":527802237,"node_id":"MDEyOklzc3VlQ29tbWVudDUyNzgwMjIzNw==","user":{"login":"Etren-zz","id":41676694,"node_id":"MDQ6VXNlcjQxNjc2Njk0","avatar_url":"https://avatars.githubusercontent.com/u/41676694?v=4","gravatar_id":"","url":"https://api.github.com/users/Etren-zz","html_url":"https://github.com/Etren-zz","followers_url":"https://api.github.com/users/Etren-zz/followers","following_url":"https://api.github.com/users/Etren-zz/following{/other_user}","gists_url":"https://api.github.com/users/Etren-zz/gists{/gist_id}","starred_url":"https://api.github.com/users/Etren-zz/starred{/owner}{/repo}","subscriptions_url":"https://api.github.com/users/Etren-zz/subscriptions","organizations_url":"https://api.github.com/users/Etren-zz/orgs","repos_url":"https://api.github.com/users/Etren-zz/repos","events_url":"https://api.github.com/users/Etren-zz/events{/privacy}","received_events_url":"https://api.github.com/users/Etren-zz/received_events","type":"User","site_admin":false},"created_at":"2019-09-04T08:37:06Z","updated_at":"2019-09-04T08:38:17Z","author_association":"NONE","body":"Although the \"Warning: multiple faces detected.\" warning was not resolved.\r\nBut after I clear the files in the `\\workspace\\data_dst\\aligned_debug` path, I restart the conversion and the conversion starts running.","reactions":{"url":"https://api.github.com/repos/iperov/DeepFaceLab/issues/comments/527802237/reactions","total_count":0,"+1":0,"-1":0,"laugh":0,"hooray":0,"confused":0,"heart":0,"rocket":0,"eyes":0},"performed_via_github_app":null,"event":"commented","actor":{"login":"Etren-zz","id":41676694,"node_id":"MDQ6VXNlcjQxNjc2Njk0","avatar_url":"https://avatars.githubusercontent.com/u/41676694?v=4","gravatar_id":"","url":"https://api.github.com/users/Etren-zz","html_url":"https://github.com/Etren-zz","followers_url":"https://api.github.com/users/Etren-zz/followers","following_url":"https://api.github.com/users/Etren-zz/following{/other_user}","gists_url":"https://api.github.com/users/Etren-zz/gists{/gist_id}","starred_url":"https://api.github.com/users/Etren-zz/starred{/owner}{/repo}","subscriptions_url":"https://api.github.com/users/Etren-zz/subscriptions","organizations_url":"https://api.github.com/users/Etren-zz/orgs","repos_url":"https://api.github.com/users/Etren-zz/repos","events_url":"https://api.github.com/users/Etren-zz/events{/privacy}","received_events_url":"https://api.github.com/users/Etren-zz/received_events","type":"User","site_admin":false}},{"url":"https://api.github.com/repos/iperov/DeepFaceLab/issues/comments/548227097","html_url":"https://github.com/iperov/DeepFaceLab/issues/390#issuecomment-548227097","issue_url":"https://api.github.com/repos/iperov/DeepFaceLab/issues/390","id":548227097,"node_id":"MDEyOklzc3VlQ29tbWVudDU0ODIyNzA5Nw==","user":{"login":"tam96","id":57208724,"node_id":"MDQ6VXNlcjU3MjA4NzI0","avatar_url":"https://avatars.githubusercontent.com/u/57208724?v=4","gravatar_id":"","url":"https://api.github.com/users/tam96","html_url":"https://github.com/tam96","followers_url":"https://api.github.com/users/tam96/followers","following_url":"https://api.github.com/users/tam96/following{/other_user}","gists_url":"https://api.github.com/users/tam96/gists{/gist_id}","starred_url":"https://api.github.com/users/tam96/starred{/owner}{/repo}","subscriptions_url":"https://api.github.com/users/tam96/subscriptions","organizations_url":"https://api.github.com/users/tam96/orgs","repos_url":"https://api.github.com/users/tam96/repos","events_url":"https://api.github.com/users/tam96/events{/privacy}","received_events_url":"https://api.github.com/users/tam96/received_events","type":"User","site_admin":false},"created_at":"2019-10-31T05:54:13Z","updated_at":"2019-10-31T05:54:13Z","author_association":"NONE","body":"I got the same error as you. can you help me. \r\n\r\n```\r\n\r\n`Running converter.\r\n\r\nUse interactive converter? (y/n skip:y) :\r\ny\r\nLoading model...\r\nUsing TensorFlow backend.\r\n=============== Model Summary ===============\r\n==                                         ==\r\n==        Model name: H64                  ==\r\n==                                         ==\r\n== Current iteration: 58981                ==\r\n==                                         ==\r\n==------------- Model Options -------------==\r\n==                                         ==\r\n==       sort_by_yaw: False                ==\r\n==       random_flip: True                 ==\r\n==        lighter_ae: False                ==\r\n==        pixel_loss: False                ==\r\n==        batch_size: 4                    ==\r\n==                                         ==\r\n==-------------- Running On ---------------==\r\n==                                         ==\r\n==      Device index: 0                    ==\r\n==              Name: GeForce GTX 1060 6GB ==\r\n==              VRAM: 6.00GB               ==\r\n==                                         ==\r\n=============================================\r\nCollecting alignments: 100%|#####################################################| 1035/1035 [00:00<00:00, 1123.00it/s]\r\nWarning: multiple faces detected. Strongly recommended to process them separately.\r\nWarning: multiple faces detected. Motion blur will not be used.\r\nUse saved session? (y/n skip:y) :\r\ny\r\nUsing saved session from model/H64_converter_session.dat\r\nRunning on CPU0.\r\nRunning on CPU1.\r\nRunning on CPU2.\r\nRunning on CPU3.\r\nRunning on CPU4.\r\nRunning on CPU5.\r\nConverting:   0%|                                                                             | 0/1146 [00:00<?, ?it/s]\r\n\r\nConverterConfig 00001.png:\r\nMode: overlay\r\nmask_mode: learned\r\nerode_mask_modifier: 0\r\nblur_mask_modifier: 0\r\nmotion_blur_power: 0\r\noutput_face_scale: 0\r\ncolor_transfer_mode: None\r\nsharpen_mode : None\r\nblursharpen_amount : 0\r\nsuper_resolution_mode : None\r\ncolor_degrade_power: 0\r\nexport_mask_alpha: False\r\n================\r\n`\r\n\r\n```","reactions":{"url":"https://api.github.com/repos/iperov/DeepFaceLab/issues/comments/548227097/reactions","total_count":0,"+1":0,"-1":0,"laugh":0,"hooray":0,"confused":0,"heart":0,"rocket":0,"eyes":0},"performed_via_github_app":null,"event":"commented","actor":{"login":"tam96","id":57208724,"node_id":"MDQ6VXNlcjU3MjA4NzI0","avatar_url":"https://avatars.githubusercontent.com/u/57208724?v=4","gravatar_id":"","url":"https://api.github.com/users/tam96","html_url":"https://github.com/tam96","followers_url":"https://api.github.com/users/tam96/followers","following_url":"https://api.github.com/users/tam96/following{/other_user}","gists_url":"https://api.github.com/users/tam96/gists{/gist_id}","starred_url":"https://api.github.com/users/tam96/starred{/owner}{/repo}","subscriptions_url":"https://api.github.com/users/tam96/subscriptions","organizations_url":"https://api.github.com/users/tam96/orgs","repos_url":"https://api.github.com/users/tam96/repos","events_url":"https://api.github.com/users/tam96/events{/privacy}","received_events_url":"https://api.github.com/users/tam96/received_events","type":"User","site_admin":false}},{"id":3174666363,"node_id":"MDExOkNsb3NlZEV2ZW50MzE3NDY2NjM2Mw==","url":"https://api.github.com/repos/iperov/DeepFaceLab/issues/events/3174666363","actor":{"login":"iperov","id":8076202,"node_id":"MDQ6VXNlcjgwNzYyMDI=","avatar_url":"https://avatars.githubusercontent.com/u/8076202?v=4","gravatar_id":"","url":"https://api.github.com/users/iperov","html_url":"https://github.com/iperov","followers_url":"https://api.github.com/users/iperov/followers","following_url":"https://api.github.com/users/iperov/following{/other_user}","gists_url":"https://api.github.com/users/iperov/gists{/gist_id}","starred_url":"https://api.github.com/users/iperov/starred{/owner}{/repo}","subscriptions_url":"https://api.github.com/users/iperov/subscriptions","organizations_url":"https://api.github.com/users/iperov/orgs","repos_url":"https://api.github.com/users/iperov/repos","events_url":"https://api.github.com/users/iperov/events{/privacy}","received_events_url":"https://api.github.com/users/iperov/received_events","type":"User","site_admin":false},"event":"closed","commit_id":null,"commit_url":null,"created_at":"2020-03-28T05:41:09Z","state_reason":null,"performed_via_github_app":null}]