{"url":"https://api.github.com/repos/developmentseed/label-maker/issues/65","repository_url":"https://api.github.com/repos/developmentseed/label-maker","labels_url":"https://api.github.com/repos/developmentseed/label-maker/issues/65/labels{/name}","comments_url":"https://api.github.com/repos/developmentseed/label-maker/issues/65/comments","events_url":"https://api.github.com/repos/developmentseed/label-maker/issues/65/events","html_url":"https://github.com/developmentseed/label-maker/issues/65","id":312634949,"node_id":"MDU6SXNzdWUzMTI2MzQ5NDk=","number":65,"title":"Include a pre-trained model example?","user":{"login":"tmcw","id":32314,"node_id":"MDQ6VXNlcjMyMzE0","avatar_url":"https://avatars.githubusercontent.com/u/32314?v=4","gravatar_id":"","url":"https://api.github.com/users/tmcw","html_url":"https://github.com/tmcw","followers_url":"https://api.github.com/users/tmcw/followers","following_url":"https://api.github.com/users/tmcw/following{/other_user}","gists_url":"https://api.github.com/users/tmcw/gists{/gist_id}","starred_url":"https://api.github.com/users/tmcw/starred{/owner}{/repo}","subscriptions_url":"https://api.github.com/users/tmcw/subscriptions","organizations_url":"https://api.github.com/users/tmcw/orgs","repos_url":"https://api.github.com/users/tmcw/repos","events_url":"https://api.github.com/users/tmcw/events{/privacy}","received_events_url":"https://api.github.com/users/tmcw/received_events","type":"User","site_admin":false},"labels":[],"state":"closed","locked":false,"assignee":null,"assignees":[],"milestone":null,"comments":2,"created_at":"2018-04-09T18:20:24Z","updated_at":"2020-12-26T21:03:34Z","closed_at":"2020-12-26T21:03:34Z","author_association":"NONE","active_lock_reason":null,"body":"Hi folks!\r\n\r\nOver at @observablehq we've been having fun using TensorFlow.js to run lightweight ML models in-browser, like [in this recent example](https://beta.observablehq.com/@nsthorat/visualizing-activations-of-mobilenet-with-tensorflow-js).\r\n\r\nI'd love to tinker with the same idea with a map-trained model, and wonder if the project might include a TensorFlow SavedModel or Keras pre-trained model as a starting point, or as part of the detailed walk-throughs. Would this be in-scope of the project, as a way to play around with the model's activations without needing to setup & train it from scratch?","closed_by":{"login":"tmcw","id":32314,"node_id":"MDQ6VXNlcjMyMzE0","avatar_url":"https://avatars.githubusercontent.com/u/32314?v=4","gravatar_id":"","url":"https://api.github.com/users/tmcw","html_url":"https://github.com/tmcw","followers_url":"https://api.github.com/users/tmcw/followers","following_url":"https://api.github.com/users/tmcw/following{/other_user}","gists_url":"https://api.github.com/users/tmcw/gists{/gist_id}","starred_url":"https://api.github.com/users/tmcw/starred{/owner}{/repo}","subscriptions_url":"https://api.github.com/users/tmcw/subscriptions","organizations_url":"https://api.github.com/users/tmcw/orgs","repos_url":"https://api.github.com/users/tmcw/repos","events_url":"https://api.github.com/users/tmcw/events{/privacy}","received_events_url":"https://api.github.com/users/tmcw/received_events","type":"User","site_admin":false},"reactions":{"url":"https://api.github.com/repos/developmentseed/label-maker/issues/65/reactions","total_count":0,"+1":0,"-1":0,"laugh":0,"hooray":0,"confused":0,"heart":0,"rocket":0,"eyes":0},"timeline_url":"https://api.github.com/repos/developmentseed/label-maker/issues/65/timeline","performed_via_github_app":null,"state_reason":"completed"}