{"url":"https://api.github.com/repos/k4yt3x/video2x/issues/700","repository_url":"https://api.github.com/repos/k4yt3x/video2x","labels_url":"https://api.github.com/repos/k4yt3x/video2x/issues/700/labels{/name}","comments_url":"https://api.github.com/repos/k4yt3x/video2x/issues/700/comments","events_url":"https://api.github.com/repos/k4yt3x/video2x/issues/700/events","html_url":"https://github.com/k4yt3x/video2x/issues/700","id":1361109114,"node_id":"I_kwDOB1EkMc5RIOB6","number":700,"title":"input output path type mismatch","user":{"login":"jalalmansour","id":42254243,"node_id":"MDQ6VXNlcjQyMjU0MjQz","avatar_url":"https://avatars.githubusercontent.com/u/42254243?v=4","gravatar_id":"","url":"https://api.github.com/users/jalalmansour","html_url":"https://github.com/jalalmansour","followers_url":"https://api.github.com/users/jalalmansour/followers","following_url":"https://api.github.com/users/jalalmansour/following{/other_user}","gists_url":"https://api.github.com/users/jalalmansour/gists{/gist_id}","starred_url":"https://api.github.com/users/jalalmansour/starred{/owner}{/repo}","subscriptions_url":"https://api.github.com/users/jalalmansour/subscriptions","organizations_url":"https://api.github.com/users/jalalmansour/orgs","repos_url":"https://api.github.com/users/jalalmansour/repos","events_url":"https://api.github.com/users/jalalmansour/events{/privacy}","received_events_url":"https://api.github.com/users/jalalmansour/received_events","type":"User","site_admin":false},"labels":[],"state":"closed","locked":false,"assignee":null,"assignees":[],"milestone":null,"comments":3,"created_at":"2022-09-04T10:40:24Z","updated_at":"2022-09-11T03:06:35Z","closed_at":"2022-09-04T22:33:16Z","author_association":"NONE","active_lock_reason":null,"body":"it simply doens't work","closed_by":{"login":"k4yt3x","id":21986859,"node_id":"MDQ6VXNlcjIxOTg2ODU5","avatar_url":"https://avatars.githubusercontent.com/u/21986859?v=4","gravatar_id":"","url":"https://api.github.com/users/k4yt3x","html_url":"https://github.com/k4yt3x","followers_url":"https://api.github.com/users/k4yt3x/followers","following_url":"https://api.github.com/users/k4yt3x/following{/other_user}","gists_url":"https://api.github.com/users/k4yt3x/gists{/gist_id}","starred_url":"https://api.github.com/users/k4yt3x/starred{/owner}{/repo}","subscriptions_url":"https://api.github.com/users/k4yt3x/subscriptions","organizations_url":"https://api.github.com/users/k4yt3x/orgs","repos_url":"https://api.github.com/users/k4yt3x/repos","events_url":"https://api.github.com/users/k4yt3x/events{/privacy}","received_events_url":"https://api.github.com/users/k4yt3x/received_events","type":"User","site_admin":false},"reactions":{"url":"https://api.github.com/repos/k4yt3x/video2x/issues/700/reactions","total_count":0,"+1":0,"-1":0,"laugh":0,"hooray":0,"confused":0,"heart":0,"rocket":0,"eyes":0},"timeline_url":"https://api.github.com/repos/k4yt3x/video2x/issues/700/timeline","performed_via_github_app":null,"state_reason":"completed"}