[{"id":2779131549,"node_id":"MDEyOkxhYmVsZWRFdmVudDI3NzkxMzE1NDk=","url":"https://api.github.com/repos/k4yt3x/video2x/issues/events/2779131549","actor":{"login":"zhangboyang","id":7912829,"node_id":"MDQ6VXNlcjc5MTI4Mjk=","avatar_url":"https://avatars.githubusercontent.com/u/7912829?v=4","gravatar_id":"","url":"https://api.github.com/users/zhangboyang","html_url":"https://github.com/zhangboyang","followers_url":"https://api.github.com/users/zhangboyang/followers","following_url":"https://api.github.com/users/zhangboyang/following{/other_user}","gists_url":"https://api.github.com/users/zhangboyang/gists{/gist_id}","starred_url":"https://api.github.com/users/zhangboyang/starred{/owner}{/repo}","subscriptions_url":"https://api.github.com/users/zhangboyang/subscriptions","organizations_url":"https://api.github.com/users/zhangboyang/orgs","repos_url":"https://api.github.com/users/zhangboyang/repos","events_url":"https://api.github.com/users/zhangboyang/events{/privacy}","received_events_url":"https://api.github.com/users/zhangboyang/received_events","type":"User","site_admin":false},"event":"labeled","commit_id":null,"commit_url":null,"created_at":"2019-11-07T12:20:31Z","label":{"name":"bug","color":"d80000"},"performed_via_github_app":null},{"id":2779131558,"node_id":"MDEzOkFzc2lnbmVkRXZlbnQyNzc5MTMxNTU4","url":"https://api.github.com/repos/k4yt3x/video2x/issues/events/2779131558","actor":{"login":"zhangboyang","id":7912829,"node_id":"MDQ6VXNlcjc5MTI4Mjk=","avatar_url":"https://avatars.githubusercontent.com/u/7912829?v=4","gravatar_id":"","url":"https://api.github.com/users/zhangboyang","html_url":"https://github.com/zhangboyang","followers_url":"https://api.github.com/users/zhangboyang/followers","following_url":"https://api.github.com/users/zhangboyang/following{/other_user}","gists_url":"https://api.github.com/users/zhangboyang/gists{/gist_id}","starred_url":"https://api.github.com/users/zhangboyang/starred{/owner}{/repo}","subscriptions_url":"https://api.github.com/users/zhangboyang/subscriptions","organizations_url":"https://api.github.com/users/zhangboyang/orgs","repos_url":"https://api.github.com/users/zhangboyang/repos","events_url":"https://api.github.com/users/zhangboyang/events{/privacy}","received_events_url":"https://api.github.com/users/zhangboyang/received_events","type":"User","site_admin":false},"event":"assigned","commit_id":null,"commit_url":null,"created_at":"2019-11-07T12:20:32Z","assignee":{"login":"k4yt3x","id":21986859,"node_id":"MDQ6VXNlcjIxOTg2ODU5","avatar_url":"https://avatars.githubusercontent.com/u/21986859?v=4","gravatar_id":"","url":"https://api.github.com/users/k4yt3x","html_url":"https://github.com/k4yt3x","followers_url":"https://api.github.com/users/k4yt3x/followers","following_url":"https://api.github.com/users/k4yt3x/following{/other_user}","gists_url":"https://api.github.com/users/k4yt3x/gists{/gist_id}","starred_url":"https://api.github.com/users/k4yt3x/starred{/owner}{/repo}","subscriptions_url":"https://api.github.com/users/k4yt3x/subscriptions","organizations_url":"https://api.github.com/users/k4yt3x/orgs","repos_url":"https://api.github.com/users/k4yt3x/repos","events_url":"https://api.github.com/users/k4yt3x/events{/privacy}","received_events_url":"https://api.github.com/users/k4yt3x/received_events","type":"User","site_admin":false},"performed_via_github_app":null},{"url":"https://api.github.com/repos/k4yt3x/video2x/issues/comments/551057634","html_url":"https://github.com/k4yt3x/video2x/issues/160#issuecomment-551057634","issue_url":"https://api.github.com/repos/k4yt3x/video2x/issues/160","id":551057634,"node_id":"MDEyOklzc3VlQ29tbWVudDU1MTA1NzYzNA==","user":{"login":"zhangboyang","id":7912829,"node_id":"MDQ6VXNlcjc5MTI4Mjk=","avatar_url":"https://avatars.githubusercontent.com/u/7912829?v=4","gravatar_id":"","url":"https://api.github.com/users/zhangboyang","html_url":"https://github.com/zhangboyang","followers_url":"https://api.github.com/users/zhangboyang/followers","following_url":"https://api.github.com/users/zhangboyang/following{/other_user}","gists_url":"https://api.github.com/users/zhangboyang/gists{/gist_id}","starred_url":"https://api.github.com/users/zhangboyang/starred{/owner}{/repo}","subscriptions_url":"https://api.github.com/users/zhangboyang/subscriptions","organizations_url":"https://api.github.com/users/zhangboyang/orgs","repos_url":"https://api.github.com/users/zhangboyang/repos","events_url":"https://api.github.com/users/zhangboyang/events{/privacy}","received_events_url":"https://api.github.com/users/zhangboyang/received_events","type":"User","site_admin":false},"created_at":"2019-11-07T12:22:56Z","updated_at":"2019-11-07T12:22:56Z","author_association":"NONE","body":"I looked into `video2x_setup.py`, it seems there should be a `video2x.json` template packaged into release package.","reactions":{"url":"https://api.github.com/repos/k4yt3x/video2x/issues/comments/551057634/reactions","total_count":0,"+1":0,"-1":0,"laugh":0,"hooray":0,"confused":0,"heart":0,"rocket":0,"eyes":0},"performed_via_github_app":null,"event":"commented","actor":{"login":"zhangboyang","id":7912829,"node_id":"MDQ6VXNlcjc5MTI4Mjk=","avatar_url":"https://avatars.githubusercontent.com/u/7912829?v=4","gravatar_id":"","url":"https://api.github.com/users/zhangboyang","html_url":"https://github.com/zhangboyang","followers_url":"https://api.github.com/users/zhangboyang/followers","following_url":"https://api.github.com/users/zhangboyang/following{/other_user}","gists_url":"https://api.github.com/users/zhangboyang/gists{/gist_id}","starred_url":"https://api.github.com/users/zhangboyang/starred{/owner}{/repo}","subscriptions_url":"https://api.github.com/users/zhangboyang/subscriptions","organizations_url":"https://api.github.com/users/zhangboyang/orgs","repos_url":"https://api.github.com/users/zhangboyang/repos","events_url":"https://api.github.com/users/zhangboyang/events{/privacy}","received_events_url":"https://api.github.com/users/zhangboyang/received_events","type":"User","site_admin":false}},{"url":"https://api.github.com/repos/k4yt3x/video2x/issues/comments/551167727","html_url":"https://github.com/k4yt3x/video2x/issues/160#issuecomment-551167727","issue_url":"https://api.github.com/repos/k4yt3x/video2x/issues/160","id":551167727,"node_id":"MDEyOklzc3VlQ29tbWVudDU1MTE2NzcyNw==","user":{"login":"k4yt3x","id":21986859,"node_id":"MDQ6VXNlcjIxOTg2ODU5","avatar_url":"https://avatars.githubusercontent.com/u/21986859?v=4","gravatar_id":"","url":"https://api.github.com/users/k4yt3x","html_url":"https://github.com/k4yt3x","followers_url":"https://api.github.com/users/k4yt3x/followers","following_url":"https://api.github.com/users/k4yt3x/following{/other_user}","gists_url":"https://api.github.com/users/k4yt3x/gists{/gist_id}","starred_url":"https://api.github.com/users/k4yt3x/starred{/owner}{/repo}","subscriptions_url":"https://api.github.com/users/k4yt3x/subscriptions","organizations_url":"https://api.github.com/users/k4yt3x/orgs","repos_url":"https://api.github.com/users/k4yt3x/repos","events_url":"https://api.github.com/users/k4yt3x/events{/privacy}","received_events_url":"https://api.github.com/users/k4yt3x/received_events","type":"User","site_admin":false},"created_at":"2019-11-07T16:54:49Z","updated_at":"2019-11-07T16:54:49Z","author_association":"OWNER","body":"You are right, there should be a JSON file there. I just haven't got time to do that yet, I'm just buried in dues after dues right now. I'll do it later today.","reactions":{"url":"https://api.github.com/repos/k4yt3x/video2x/issues/comments/551167727/reactions","total_count":0,"+1":0,"-1":0,"laugh":0,"hooray":0,"confused":0,"heart":0,"rocket":0,"eyes":0},"performed_via_github_app":null,"event":"commented","actor":{"login":"k4yt3x","id":21986859,"node_id":"MDQ6VXNlcjIxOTg2ODU5","avatar_url":"https://avatars.githubusercontent.com/u/21986859?v=4","gravatar_id":"","url":"https://api.github.com/users/k4yt3x","html_url":"https://github.com/k4yt3x","followers_url":"https://api.github.com/users/k4yt3x/followers","following_url":"https://api.github.com/users/k4yt3x/following{/other_user}","gists_url":"https://api.github.com/users/k4yt3x/gists{/gist_id}","starred_url":"https://api.github.com/users/k4yt3x/starred{/owner}{/repo}","subscriptions_url":"https://api.github.com/users/k4yt3x/subscriptions","organizations_url":"https://api.github.com/users/k4yt3x/orgs","repos_url":"https://api.github.com/users/k4yt3x/repos","events_url":"https://api.github.com/users/k4yt3x/events{/privacy}","received_events_url":"https://api.github.com/users/k4yt3x/received_events","type":"User","site_admin":false}},{"id":2780091279,"node_id":"MDExOkNsb3NlZEV2ZW50Mjc4MDA5MTI3OQ==","url":"https://api.github.com/repos/k4yt3x/video2x/issues/events/2780091279","actor":{"login":"k4yt3x","id":21986859,"node_id":"MDQ6VXNlcjIxOTg2ODU5","avatar_url":"https://avatars.githubusercontent.com/u/21986859?v=4","gravatar_id":"","url":"https://api.github.com/users/k4yt3x","html_url":"https://github.com/k4yt3x","followers_url":"https://api.github.com/users/k4yt3x/followers","following_url":"https://api.github.com/users/k4yt3x/following{/other_user}","gists_url":"https://api.github.com/users/k4yt3x/gists{/gist_id}","starred_url":"https://api.github.com/users/k4yt3x/starred{/owner}{/repo}","subscriptions_url":"https://api.github.com/users/k4yt3x/subscriptions","organizations_url":"https://api.github.com/users/k4yt3x/orgs","repos_url":"https://api.github.com/users/k4yt3x/repos","events_url":"https://api.github.com/users/k4yt3x/events{/privacy}","received_events_url":"https://api.github.com/users/k4yt3x/received_events","type":"User","site_admin":false},"event":"closed","commit_id":null,"commit_url":null,"created_at":"2019-11-07T16:54:49Z","state_reason":null,"performed_via_github_app":null}]