{"url":"https://api.github.com/repos/Daniil-Osokin/lightweight-human-pose-estimation.pytorch/issues/135","repository_url":"https://api.github.com/repos/Daniil-Osokin/lightweight-human-pose-estimation.pytorch","labels_url":"https://api.github.com/repos/Daniil-Osokin/lightweight-human-pose-estimation.pytorch/issues/135/labels{/name}","comments_url":"https://api.github.com/repos/Daniil-Osokin/lightweight-human-pose-estimation.pytorch/issues/135/comments","events_url":"https://api.github.com/repos/Daniil-Osokin/lightweight-human-pose-estimation.pytorch/issues/135/events","html_url":"https://github.com/Daniil-Osokin/lightweight-human-pose-estimation.pytorch/issues/135","id":819788792,"node_id":"MDU6SXNzdWU4MTk3ODg3OTI=","number":135,"title":"Does the paf map generated by the network affect the occlusion of some key points of the human body？","user":{"login":"tangfayuan","id":67772825,"node_id":"MDQ6VXNlcjY3NzcyODI1","avatar_url":"https://avatars.githubusercontent.com/u/67772825?v=4","gravatar_id":"","url":"https://api.github.com/users/tangfayuan","html_url":"https://github.com/tangfayuan","followers_url":"https://api.github.com/users/tangfayuan/followers","following_url":"https://api.github.com/users/tangfayuan/following{/other_user}","gists_url":"https://api.github.com/users/tangfayuan/gists{/gist_id}","starred_url":"https://api.github.com/users/tangfayuan/starred{/owner}{/repo}","subscriptions_url":"https://api.github.com/users/tangfayuan/subscriptions","organizations_url":"https://api.github.com/users/tangfayuan/orgs","repos_url":"https://api.github.com/users/tangfayuan/repos","events_url":"https://api.github.com/users/tangfayuan/events{/privacy}","received_events_url":"https://api.github.com/users/tangfayuan/received_events","type":"User","site_admin":false},"labels":[],"state":"closed","locked":false,"assignee":null,"assignees":[],"milestone":null,"comments":7,"created_at":"2021-03-02T08:44:01Z","updated_at":"2021-03-09T19:31:03Z","closed_at":"2021-03-09T19:31:03Z","author_association":"NONE","active_lock_reason":null,"body":"","closed_by":{"login":"Daniil-Osokin","id":2491976,"node_id":"MDQ6VXNlcjI0OTE5NzY=","avatar_url":"https://avatars.githubusercontent.com/u/2491976?v=4","gravatar_id":"","url":"https://api.github.com/users/Daniil-Osokin","html_url":"https://github.com/Daniil-Osokin","followers_url":"https://api.github.com/users/Daniil-Osokin/followers","following_url":"https://api.github.com/users/Daniil-Osokin/following{/other_user}","gists_url":"https://api.github.com/users/Daniil-Osokin/gists{/gist_id}","starred_url":"https://api.github.com/users/Daniil-Osokin/starred{/owner}{/repo}","subscriptions_url":"https://api.github.com/users/Daniil-Osokin/subscriptions","organizations_url":"https://api.github.com/users/Daniil-Osokin/orgs","repos_url":"https://api.github.com/users/Daniil-Osokin/repos","events_url":"https://api.github.com/users/Daniil-Osokin/events{/privacy}","received_events_url":"https://api.github.com/users/Daniil-Osokin/received_events","type":"User","site_admin":false},"reactions":{"url":"https://api.github.com/repos/Daniil-Osokin/lightweight-human-pose-estimation.pytorch/issues/135/reactions","total_count":0,"+1":0,"-1":0,"laugh":0,"hooray":0,"confused":0,"heart":0,"rocket":0,"eyes":0},"timeline_url":"https://api.github.com/repos/Daniil-Osokin/lightweight-human-pose-estimation.pytorch/issues/135/timeline","performed_via_github_app":null,"state_reason":"completed"}